pup517/__about__.py
pup517/__init__.py
pup517/backend.py
pup517/fetch.py
pup517/pkg.py
pup517/build_system/__init__.py
pup517/build_system/base.py
pup517/build_system/simple_cc.py
pup517-0.0.3.dist-info/METADATA
pup517-0.0.3.dist-info/WHEEL
pup517-0.0.3.dist-info/licenses/LICENSE.txt
pup517-0.0.3.dist-info/RECORD
