Metadata-Version: 2.4
Name: pup517
Version: 0.0.3
Summary: Python Universal Packager
Project-URL: Documentation, https://github.com/jackrosenthal/pup517#readme
Project-URL: Issues, https://github.com/jackrosenthal/pup517/issues
Project-URL: Source, https://github.com/jackrosenthal/pup517
Author-email: Jack Rosenthal <jack@rosenth.al>
License-Expression: MIT
License-File: LICENSE.txt
Classifier: Development Status :: 4 - Beta
Classifier: Programming Language :: Python
Classifier: Programming Language :: Python :: 3.11
Classifier: Programming Language :: Python :: 3.12
Classifier: Programming Language :: Python :: Implementation :: CPython
Classifier: Programming Language :: Python :: Implementation :: PyPy
Requires-Python: >=3.11
Requires-Dist: pydantic>=2.0
Requires-Dist: wheel
